{"textures":{"1":"modelengine:entity/texture12"},"elements":[{"from":[7.369396,6.3673167,7.5],"to":[12.369396,7.3673167,8.5],"faces":{"east":{"uv":[5.75,0.5,5.875,0.625],"tintindex":0,"rotation":0,"texture":"#1"},"south":{"uv":[0.0,5.375,0.625,5.5],"tintindex":0,"rotation":0,"texture":"#1"},"north":{"uv":[4.75,3.875,5.375,4.0],"tintindex":0,"rotation":0,"texture":"#1"},"west":{"uv":[6.75,3.75,6.875,3.875],"tintindex":0,"rotation":0,"texture":"#1"},"up":{"uv":[6.125,5.25,5.5,5.125],"tintindex":0,"rotation":0,"texture":"#1"},"down":{"uv":[6.75,3.75,6.125,3.875],"tintindex":0,"rotation":0,"texture":"#1"}},"rotation":{"origin":[11.021639,6.1019497,8.0],"angle":-22.5,"axis":"z"}}],"display":{"gui":{"rotation":[30,225,0]}}}